{
  "red": "red",
  "shirt": "shirt",
  "blue": "blue",
  "jacket": "jacket",
  "green": "green",
  "pants": "pants",
  "black": "black",
  "hat": "hat",
  "white": "white",
  "shoes": "shoes",
  "yellow": "yellow",
  "dresses": "dresses",
  "pink": "pink",
  "scarf": "scarf",
  "dress": "dress",
  "burgundy": "burgundy",
  "navy": "navy",
  "purple": "purple",
  "sweater": "sweater",
  "teal": "teal",
  "skirts": "skirts",
  "gray": "gray",
  "blazers": "blazers",
  "striped": "striped",
  "shirts": "shirts",
  "brown": "brown",
  "sneakers": "sneakers",
  "vintage": "vintage",
  "tshirt": "tshirt",
  "blouse": "blouse",
  "coats": "coats",
  "shorts": "shorts",
  "jeans": "jeans",
  "hoodie": "hoodie",
  "sweatpants": "sweatpants",
  "skirt": "skirt",
  "coat": "coat",
  "nike dunks": "Nike Dunks",
  "puma shoes": "Puma shoes",
  "adidas sneakers": "Adidas sneakers",
  "levi's jeans": "Levi's jeans",
  "converse": "Converse",
  "air jordans": "Air Jordans",
  "vans old skool": "Vans Old Skool",
  "north face jacket": "North Face jacket",
  "ralph lauren polo": "Ralph Lauren polo",
  "champion hoodie": "Champion hoodie",
  "doc martens": "Doc Martens",
  "birkenstock sandals": "Birkenstock sandals",
  "carhartt pants": "Carhartt pants",
  "zara dress": "Zara dress",
  "h&m blazer": "H&M blazer",
  "uniqlo jacket": "Uniqlo jacket",
  "lamelo ball shoes": "LaMelo Ball shoes",
  "gildan t-shirt": "Gildan t-shirt",
  "blazer": "blazer",
  "t-shirt": "t-shirt",
  "cardigan": "cardigan",
  "olive": "olive",
  "maroon": "maroon"
}